; Inet4Address-classtable.lisp
; Automatically generated by jvm2acl2 on Tue May 27 00:39:37 CDT 2014.
;

(defconst *java.net.Inet4Address*
 (make-class-def
      '(class "java.net.Inet4Address"
            "java.net.InetAddress"
            (constant_pool
                        (INT 4)
                        (LONG 3286316764910316507)
                        (INT 2130706433)
                        (INT 65280)
                        (INT 16711680)
                        (INT -16777216)
                        (INT -268435456)
                        (INT -536870912)
                        (STRING  "."))
            (fields
                        (field "INADDRSZ" int (accessflags  *class*  *final*  *static* ) 0)
                        (field "serialVersionUID" long (accessflags  *class*  *final*  *private*  *static* ) 1)
                        (field "loopback" int (accessflags  *class*  *final*  *private*  *static* ) 2))
            (methods
                        (method "<init>"
                              (parameters )
                              (returntype . void)
                              (accessflags  *class* )
                              (code
                                   (max_stack . 2) (max_locals . 1) (code_length . 20)
                                   (parsedcode
                                      (0 (aload_0))
                                      (1 (invokespecial
					(methodCP "<init>" "java.net.InetAddress" () void)))
                                      (4 (aload_0))
                                      (5 (aconst_null))
                                      (6 (putfield (fieldCP "hostName" "java.net.Inet4Address" (class "java.lang.String"))))
                                      (9 (aload_0))
                                      (10 (iconst_0))
                                      (11 (putfield (fieldCP "address" "java.net.Inet4Address" int)))
                                      (14 (aload_0))
                                      (15 (iconst_1))
                                      (16 (putfield (fieldCP "family" "java.net.Inet4Address" int)))
                                      (19 (return))
                                      (endofcode 20))
                                   (Exceptions )
                                   (StackMap )))
                        (method "<init>"
                              (parameters (class "java.lang.String") (array byte))
                              (returntype . void)
                              (accessflags  *class* )
                              (code
                                   (max_stack . 4) (max_locals . 3) (code_length . 90)
                                   (parsedcode
                                      (0 (aload_0)) 
                                      (1 (invokespecial (methodCP "<init>" "java.net.InetAddress" () void))) 
                                      (4 (aload_0)) 
                                      (5 (aload_1)) 
                                      (6 (putfield (fieldCP "hostName" "java.net.Inet4Address" (class "java.lang.String")))) 
                                      (9 (aload_0)) 
                                      (10 (iconst_1)) 
                                      (11 (putfield (fieldCP "family" "java.net.Inet4Address" int))) 
                                      (14 (aload_2)) 
                                      (15 (ifnull 89))  ;;to TAG_0
                                      (18 (aload_2)) 
                                      (19 (arraylength)) 
                                      (20 (iconst_4)) 
                                      (21 (if_icmpne 89))  ;;to TAG_0
                                      (24 (aload_0)) 
                                      (25 (aload_2)) 
                                      (26 (iconst_3)) 
                                      (27 (baload)) 
                                      (28 (sipush 255)) 
                                      (31 (iand)) 
                                      (32 (putfield (fieldCP "address" "java.net.Inet4Address" int))) 
                                      (35 (aload_0)) 
                                      (36 (dup)) 
                                      (37 (getfield (fieldCP "address" "java.net.Inet4Address" int))) 
                                      (40 (aload_2)) 
                                      (41 (iconst_2)) 
                                      (42 (baload)) 
                                      (43 (bipush 8)) 
                                      (45 (ishl)) 
                                      (46 (ldc 3)) ;;INT:: "65280"
                                      (48 (iand)) 
                                      (49 (ior)) 
                                      (50 (putfield (fieldCP "address" "java.net.Inet4Address" int))) 
                                      (53 (aload_0)) 
                                      (54 (dup)) 
                                      (55 (getfield (fieldCP "address" "java.net.Inet4Address" int))) 
                                      (58 (aload_2)) 
                                      (59 (iconst_1)) 
                                      (60 (baload)) 
                                      (61 (bipush 16)) 
                                      (63 (ishl)) 
                                      (64 (ldc 4)) ;;INT:: "16711680"
                                      (66 (iand)) 
                                      (67 (ior)) 
                                      (68 (putfield (fieldCP "address" "java.net.Inet4Address" int))) 
                                      (71 (aload_0)) 
                                      (72 (dup)) 
                                      (73 (getfield (fieldCP "address" "java.net.Inet4Address" int))) 
                                      (76 (aload_2)) 
                                      (77 (iconst_0)) 
                                      (78 (baload)) 
                                      (79 (bipush 24)) 
                                      (81 (ishl)) 
                                      (82 (ldc 5)) ;;INT:: "-16777216"
                                      (84 (iand)) 
                                      (85 (ior)) 
                                      (86 (putfield (fieldCP "address" "java.net.Inet4Address" int))) 
                                      (89 (return)) ;;at TAG_0
                                      (endofcode 90))
                                   (Exceptions )
                                   (StackMap )))
                        (method "<init>"
                              (parameters (class "java.lang.String") int)
                              (returntype . void)
                              (accessflags  *class* )
                              (code
                                   (max_stack . 2) (max_locals . 3) (code_length . 20)
                                   (parsedcode
                                      (0 (aload_0))
                                      (1 (invokespecial
					(methodCP "<init>" "java.net.InetAddress" () void)))
                                      (4 (aload_0))
                                      (5 (aload_1))
                                      (6 (putfield (fieldCP "hostName" "java.net.Inet4Address" (class "java.lang.String"))))
                                      (9 (aload_0))
                                      (10 (iconst_1))
                                      (11 (putfield (fieldCP "family" "java.net.Inet4Address" int)))
                                      (14 (aload_0))
                                      (15 (iload_2))
                                      (16 (putfield (fieldCP "address" "java.net.Inet4Address" int)))
                                      (19 (return))
                                      (endofcode 20))
                                   (Exceptions )
                                   (StackMap )))
                        (method "writeReplace"
                              (parameters )
                              (returntype . (class "java.lang.Object"))
                              (accessflags  *class*  *private* )
                              (code
                                   (max_stack . 2) (max_locals . 2) (code_length . 31)
                                   (parsedcode
                                      (0 (new (class "java.net.InetAddress")))
                                      (3 (dup))
                                      (4 (invokespecial
					(methodCP "<init>" "java.net.InetAddress" () void)))
                                      (7 (astore_1))
                                      (8 (aload_1))
                                      (9 (aload_0))
                                      (10 (getfield (fieldCP "hostName" "java.net.Inet4Address" (class "java.lang.String"))))
                                      (13 (putfield (fieldCP "hostName" "java.net.InetAddress" (class "java.lang.String"))))
                                      (16 (aload_1))
                                      (17 (aload_0))
                                      (18 (getfield (fieldCP "address" "java.net.Inet4Address" int)))
                                      (21 (putfield (fieldCP "address" "java.net.InetAddress" int)))
                                      (24 (aload_1))
                                      (25 (iconst_2))
                                      (26 (putfield (fieldCP "family" "java.net.InetAddress" int)))
                                      (29 (aload_1))
                                      (30 (areturn))
                                      (endofcode 31))
                                   (Exceptions )
                                   (StackMap )))
                        (method "isMulticastAddress"
                              (parameters )
                              (returntype . boolean)
                              (accessflags  *class*  *public* )
                              (code
                                   (max_stack . 2) (max_locals . 1) (code_length . 18)
                                   (parsedcode
                                      (0 (aload_0)) 
                                      (1 (getfield (fieldCP "address" "java.net.Inet4Address" int))) 
                                      (4 (ldc 6)) ;;INT:: "-268435456"
                                      (6 (iand)) 
                                      (7 (ldc 7)) ;;INT:: "-536870912"
                                      (9 (if_icmpne 16))  ;;to TAG_0
                                      (12 (iconst_1)) 
                                      (13 (goto 17)) ;;to TAG_1
                                      (16 (iconst_0)) ;;at TAG_0
                                      (17 (ireturn)) ;;at TAG_1
                                      (endofcode 18))
                                   (Exceptions )
                                   (StackMap )))
                        (method "isAnyLocalAddress"
                              (parameters )
                              (returntype . boolean)
                              (accessflags  *class*  *public* )
                              (code
                                   (max_stack . 1) (max_locals . 1) (code_length . 13)
                                   (parsedcode
                                      (0 (aload_0)) 
                                      (1 (getfield (fieldCP "address" "java.net.Inet4Address" int))) 
                                      (4 (ifne 11))  ;;to TAG_0
                                      (7 (iconst_1)) 
                                      (8 (goto 12)) ;;to TAG_1
                                      (11 (iconst_0)) ;;at TAG_0
                                      (12 (ireturn)) ;;at TAG_1
                                      (endofcode 13))
                                   (Exceptions )
                                   (StackMap )))
                        (method "isLoopbackAddress"
                              (parameters )
                              (returntype . boolean)
                              (accessflags  *class*  *public* )
                              (code
                                   (max_stack . 2) (max_locals . 2) (code_length . 19)
                                   (parsedcode
                                      (0 (aload_0)) 
                                      (1 (invokevirtual (methodCP "getAddress" "java.net.Inet4Address" () (array byte)))) 
                                      (4 (astore_1)) 
                                      (5 (aload_1)) 
                                      (6 (iconst_0)) 
                                      (7 (baload)) 
                                      (8 (bipush 127)) 
                                      (10 (if_icmpne 17))  ;;to TAG_0
                                      (13 (iconst_1)) 
                                      (14 (goto 18)) ;;to TAG_1
                                      (17 (iconst_0)) ;;at TAG_0
                                      (18 (ireturn)) ;;at TAG_1
                                      (endofcode 19))
                                   (Exceptions )
                                   (StackMap )))
                        (method "isLinkLocalAddress"
                              (parameters )
                              (returntype . boolean)
                              (accessflags  *class*  *public* )
                              (code
                                   (max_stack . 2) (max_locals . 1) (code_length . 40)
                                   (parsedcode
                                      (0 (aload_0)) 
                                      (1 (getfield (fieldCP "address" "java.net.Inet4Address" int))) 
                                      (4 (bipush 24)) 
                                      (6 (iushr)) 
                                      (7 (sipush 255)) 
                                      (10 (iand)) 
                                      (11 (sipush 169)) 
                                      (14 (if_icmpne 38))  ;;to TAG_0
                                      (17 (aload_0)) 
                                      (18 (getfield (fieldCP "address" "java.net.Inet4Address" int))) 
                                      (21 (bipush 16)) 
                                      (23 (iushr)) 
                                      (24 (sipush 255)) 
                                      (27 (iand)) 
                                      (28 (sipush 254)) 
                                      (31 (if_icmpne 38))  ;;to TAG_0
                                      (34 (iconst_1)) 
                                      (35 (goto 39)) ;;to TAG_1
                                      (38 (iconst_0)) ;;at TAG_0
                                      (39 (ireturn)) ;;at TAG_1
                                      (endofcode 40))
                                   (Exceptions )
                                   (StackMap )))
                        (method "isSiteLocalAddress"
                              (parameters )
                              (returntype . boolean)
                              (accessflags  *class*  *public* )
                              (code
                                   (max_stack . 2) (max_locals . 1) (code_length . 89)
                                   (parsedcode
                                      (0 (aload_0)) 
                                      (1 (getfield (fieldCP "address" "java.net.Inet4Address" int))) 
                                      (4 (bipush 24)) 
                                      (6 (iushr)) 
                                      (7 (sipush 255)) 
                                      (10 (iand)) 
                                      (11 (bipush 10)) 
                                      (13 (if_icmpeq 83)) ;;to TAG_0
                                      (16 (aload_0)) 
                                      (17 (getfield (fieldCP "address" "java.net.Inet4Address" int))) 
                                      (20 (bipush 24)) 
                                      (22 (iushr)) 
                                      (23 (sipush 255)) 
                                      (26 (iand)) 
                                      (27 (sipush 172)) 
                                      (30 (if_icmpne 49)) ;;to TAG_1
                                      (33 (aload_0)) 
                                      (34 (getfield (fieldCP "address" "java.net.Inet4Address" int))) 
                                      (37 (bipush 16)) 
                                      (39 (iushr)) 
                                      (40 (sipush 240)) 
                                      (43 (iand)) 
                                      (44 (bipush 16)) 
                                      (46 (if_icmpeq 83)) ;;to TAG_0
                                      (49 (aload_0)) ;;at TAG_1
                                      (50 (getfield (fieldCP "address" "java.net.Inet4Address" int))) 
                                      (53 (bipush 24)) 
                                      (55 (iushr)) 
                                      (56 (sipush 255)) 
                                      (59 (iand)) 
                                      (60 (sipush 192)) 
                                      (63 (if_icmpne 87))  ;;to TAG_2
                                      (66 (aload_0)) 
                                      (67 (getfield (fieldCP "address" "java.net.Inet4Address" int))) 
                                      (70 (bipush 16)) 
                                      (72 (iushr)) 
                                      (73 (sipush 255)) 
                                      (76 (iand)) 
                                      (77 (sipush 168)) 
                                      (80 (if_icmpne 87))  ;;to TAG_2
                                      (83 (iconst_1)) ;;at TAG_0
                                      (84 (goto 88)) ;;to TAG_3
                                      (87 (iconst_0)) ;;at TAG_2
                                      (88 (ireturn)) ;;at TAG_3
                                      (endofcode 89))
                                   (Exceptions )
                                   (StackMap )))
                        (method "isMCGlobal"
                              (parameters )
                              (returntype . boolean)
                              (accessflags  *class*  *public* )
                              (code
                                   (max_stack . 2) (max_locals . 2) (code_length . 62)
                                   (parsedcode
                                      (0 (aload_0)) 
                                      (1 (invokevirtual (methodCP "getAddress" "java.net.Inet4Address" () (array byte)))) 
                                      (4 (astore_1)) 
                                      (5 (aload_1)) 
                                      (6 (iconst_0)) 
                                      (7 (baload)) 
                                      (8 (sipush 255)) 
                                      (11 (iand)) 
                                      (12 (sipush 224)) 
                                      (15 (if_icmplt 60)) ;;to TAG_0
                                      (18 (aload_1)) 
                                      (19 (iconst_0)) 
                                      (20 (baload)) 
                                      (21 (sipush 255)) 
                                      (24 (iand)) 
                                      (25 (sipush 238)) 
                                      (28 (if_icmpgt 60)) ;;to TAG_0
                                      (31 (aload_1)) 
                                      (32 (iconst_0)) 
                                      (33 (baload)) 
                                      (34 (sipush 255)) 
                                      (37 (iand)) 
                                      (38 (sipush 224)) 
                                      (41 (if_icmpne 56)) ;;to TAG_1
                                      (44 (aload_1)) 
                                      (45 (iconst_1)) 
                                      (46 (baload)) 
                                      (47 (ifne 56)) ;;to TAG_1
                                      (50 (aload_1)) 
                                      (51 (iconst_2)) 
                                      (52 (baload)) 
                                      (53 (ifeq 60)) ;;to TAG_0
                                      (56 (iconst_1)) ;;at TAG_1
                                      (57 (goto 61))  ;;to TAG_2
                                      (60 (iconst_0)) ;;at TAG_0
                                      (61 (ireturn)) ;;at TAG_2
                                      (endofcode 62))
                                   (Exceptions )
                                   (StackMap )))
                        (method "isMCNodeLocal"
                              (parameters )
                              (returntype . boolean)
                              (accessflags  *class*  *public* )
                              (code
                                   (max_stack . 1) (max_locals . 1) (code_length . 2)
                                   (parsedcode
                                      (0 (iconst_0))
                                      (1 (ireturn))
                                      (endofcode 2))
                                   (Exceptions )
                                   (StackMap )))
                        (method "isMCLinkLocal"
                              (parameters )
                              (returntype . boolean)
                              (accessflags  *class*  *public* )
                              (code
                                   (max_stack . 2) (max_locals . 1) (code_length . 51)
                                   (parsedcode
                                      (0 (aload_0)) 
                                      (1 (getfield (fieldCP "address" "java.net.Inet4Address" int))) 
                                      (4 (bipush 24)) 
                                      (6 (iushr)) 
                                      (7 (sipush 255)) 
                                      (10 (iand)) 
                                      (11 (sipush 224)) 
                                      (14 (if_icmpne 49))  ;;to TAG_0
                                      (17 (aload_0)) 
                                      (18 (getfield (fieldCP "address" "java.net.Inet4Address" int))) 
                                      (21 (bipush 16)) 
                                      (23 (iushr)) 
                                      (24 (sipush 255)) 
                                      (27 (iand)) 
                                      (28 (ifne 49))  ;;to TAG_0
                                      (31 (aload_0)) 
                                      (32 (getfield (fieldCP "address" "java.net.Inet4Address" int))) 
                                      (35 (bipush 8)) 
                                      (37 (iushr)) 
                                      (38 (sipush 255)) 
                                      (41 (iand)) 
                                      (42 (ifne 49))  ;;to TAG_0
                                      (45 (iconst_1)) 
                                      (46 (goto 50)) ;;to TAG_1
                                      (49 (iconst_0)) ;;at TAG_0
                                      (50 (ireturn)) ;;at TAG_1
                                      (endofcode 51))
                                   (Exceptions )
                                   (StackMap )))
                        (method "isMCSiteLocal"
                              (parameters )
                              (returntype . boolean)
                              (accessflags  *class*  *public* )
                              (code
                                   (max_stack . 2) (max_locals . 1) (code_length . 40)
                                   (parsedcode
                                      (0 (aload_0)) 
                                      (1 (getfield (fieldCP "address" "java.net.Inet4Address" int))) 
                                      (4 (bipush 24)) 
                                      (6 (iushr)) 
                                      (7 (sipush 255)) 
                                      (10 (iand)) 
                                      (11 (sipush 239)) 
                                      (14 (if_icmpne 38))  ;;to TAG_0
                                      (17 (aload_0)) 
                                      (18 (getfield (fieldCP "address" "java.net.Inet4Address" int))) 
                                      (21 (bipush 16)) 
                                      (23 (iushr)) 
                                      (24 (sipush 255)) 
                                      (27 (iand)) 
                                      (28 (sipush 255)) 
                                      (31 (if_icmpne 38))  ;;to TAG_0
                                      (34 (iconst_1)) 
                                      (35 (goto 39)) ;;to TAG_1
                                      (38 (iconst_0)) ;;at TAG_0
                                      (39 (ireturn)) ;;at TAG_1
                                      (endofcode 40))
                                   (Exceptions )
                                   (StackMap )))
                        (method "isMCOrgLocal"
                              (parameters )
                              (returntype . boolean)
                              (accessflags  *class*  *public* )
                              (code
                                   (max_stack . 2) (max_locals . 1) (code_length . 57)
                                   (parsedcode
                                      (0 (aload_0)) 
                                      (1 (getfield (fieldCP "address" "java.net.Inet4Address" int))) 
                                      (4 (bipush 24)) 
                                      (6 (iushr)) 
                                      (7 (sipush 255)) 
                                      (10 (iand)) 
                                      (11 (sipush 239)) 
                                      (14 (if_icmpne 55))  ;;to TAG_0
                                      (17 (aload_0)) 
                                      (18 (getfield (fieldCP "address" "java.net.Inet4Address" int))) 
                                      (21 (bipush 16)) 
                                      (23 (iushr)) 
                                      (24 (sipush 255)) 
                                      (27 (iand)) 
                                      (28 (sipush 192)) 
                                      (31 (if_icmplt 55))  ;;to TAG_0
                                      (34 (aload_0)) 
                                      (35 (getfield (fieldCP "address" "java.net.Inet4Address" int))) 
                                      (38 (bipush 16)) 
                                      (40 (iushr)) 
                                      (41 (sipush 255)) 
                                      (44 (iand)) 
                                      (45 (sipush 195)) 
                                      (48 (if_icmpgt 55))  ;;to TAG_0
                                      (51 (iconst_1)) 
                                      (52 (goto 56)) ;;to TAG_1
                                      (55 (iconst_0)) ;;at TAG_0
                                      (56 (ireturn)) ;;at TAG_1
                                      (endofcode 57))
                                   (Exceptions )
                                   (StackMap )))
                        (method "getAddress"
                              (parameters )
                              (returntype . (array byte))
                              (accessflags  *class*  *public* )
                              (code
                                   (max_stack . 4) (max_locals . 2) (code_length . 63)
                                   (parsedcode
                                      (0 (iconst_4))
                                      (1 (newarray BYTE))
                                      (3 (astore_1))
                                      (4 (aload_1))
                                      (5 (iconst_0))
                                      (6 (aload_0))
                                      (7 (getfield (fieldCP "address" "java.net.Inet4Address" int)))
                                      (10 (bipush 24))
                                      (12 (iushr))
                                      (13 (sipush 255))
                                      (16 (iand))
                                      (17 (i2b))
                                      (18 (bastore))
                                      (19 (aload_1))
                                      (20 (iconst_1))
                                      (21 (aload_0))
                                      (22 (getfield (fieldCP "address" "java.net.Inet4Address" int)))
                                      (25 (bipush 16))
                                      (27 (iushr))
                                      (28 (sipush 255))
                                      (31 (iand))
                                      (32 (i2b))
                                      (33 (bastore))
                                      (34 (aload_1))
                                      (35 (iconst_2))
                                      (36 (aload_0))
                                      (37 (getfield (fieldCP "address" "java.net.Inet4Address" int)))
                                      (40 (bipush 8))
                                      (42 (iushr))
                                      (43 (sipush 255))
                                      (46 (iand))
                                      (47 (i2b))
                                      (48 (bastore))
                                      (49 (aload_1))
                                      (50 (iconst_3))
                                      (51 (aload_0))
                                      (52 (getfield (fieldCP "address" "java.net.Inet4Address" int)))
                                      (55 (sipush 255))
                                      (58 (iand))
                                      (59 (i2b))
                                      (60 (bastore))
                                      (61 (aload_1))
                                      (62 (areturn))
                                      (endofcode 63))
                                   (Exceptions )
                                   (StackMap )))
                        (method "getHostAddress"
                              (parameters )
                              (returntype . (class "java.lang.String"))
                              (accessflags  *class*  *public* )
                              (code
                                   (max_stack . 1) (max_locals . 1) (code_length . 8)
                                   (parsedcode
                                      (0 (aload_0))
                                      (1 (invokevirtual
					(methodCP "getAddress" "java.net.Inet4Address" () (array byte))))
                                      (4 (invokestatic
					(methodCP "numericToTextFormat" "java.net.Inet4Address" ((array byte)) (class "java.lang.String"))))
                                      (7 (areturn))
                                      (endofcode 8))
                                   (Exceptions )
                                   (StackMap )))
                        (method "hashCode"
                              (parameters )
                              (returntype . int)
                              (accessflags  *class*  *public* )
                              (code
                                   (max_stack . 1) (max_locals . 1) (code_length . 5)
                                   (parsedcode
                                      (0 (aload_0))
                                      (1 (getfield (fieldCP "address" "java.net.Inet4Address" int)))
                                      (4 (ireturn))
                                      (endofcode 5))
                                   (Exceptions )
                                   (StackMap )))
                        (method "equals"
                              (parameters (class "java.lang.Object"))
                              (returntype . boolean)
                              (accessflags  *class*  *public* )
                              (code
                                   (max_stack . 2) (max_locals . 2) (code_length . 31)
                                   (parsedcode
                                      (0 (aload_1)) 
                                      (1 (ifnull 29))  ;;to TAG_0
                                      (4 (aload_1)) 
                                      (5 (instanceof (class "java.net.Inet4Address"))) 
                                      (8 (ifeq 29))  ;;to TAG_0
                                      (11 (aload_1)) 
                                      (12 (checkcast (class "java.net.InetAddress"))) 
                                      (15 (getfield (fieldCP "address" "java.net.InetAddress" int))) 
                                      (18 (aload_0)) 
                                      (19 (getfield (fieldCP "address" "java.net.Inet4Address" int))) 
                                      (22 (if_icmpne 29))  ;;to TAG_0
                                      (25 (iconst_1)) 
                                      (26 (goto 30)) ;;to TAG_1
                                      (29 (iconst_0)) ;;at TAG_0
                                      (30 (ireturn)) ;;at TAG_1
                                      (endofcode 31))
                                   (Exceptions )
                                   (StackMap )))
                        (method "numericToTextFormat"
                              (parameters (array byte))
                              (returntype . (class "java.lang.String"))
                              (accessflags  *class*  *static* )
                              (code
                                   (max_stack . 3) (max_locals . 1) (code_length . 66)
                                   (parsedcode
                                      (0 (new (class "java.lang.StringBuilder")))
                                      (3 (dup))
                                      (4 (invokespecial
					(methodCP "<init>" "java.lang.StringBuilder" () void)))
                                      (7 (aload_0))
                                      (8 (iconst_0))
                                      (9 (baload))
                                      (10 (sipush 255))
                                      (13 (iand))
                                      (14 (invokevirtual
					(methodCP "append" "java.lang.StringBuilder" (int) (class "java.lang.StringBuilder"))))
                                      (17 (ldc 8))        ;;STRING:: "."
                                      (19 (invokevirtual
					(methodCP "append" "java.lang.StringBuilder" ((class "java.lang.String")) (class "java.lang.StringBuilder"))))
                                      (22 (aload_0))
                                      (23 (iconst_1))
                                      (24 (baload))
                                      (25 (sipush 255))
                                      (28 (iand))
                                      (29 (invokevirtual
					(methodCP "append" "java.lang.StringBuilder" (int) (class "java.lang.StringBuilder"))))
                                      (32 (ldc 8))        ;;STRING:: "."
                                      (34 (invokevirtual
					(methodCP "append" "java.lang.StringBuilder" ((class "java.lang.String")) (class "java.lang.StringBuilder"))))
                                      (37 (aload_0))
                                      (38 (iconst_2))
                                      (39 (baload))
                                      (40 (sipush 255))
                                      (43 (iand))
                                      (44 (invokevirtual
					(methodCP "append" "java.lang.StringBuilder" (int) (class "java.lang.StringBuilder"))))
                                      (47 (ldc 8))        ;;STRING:: "."
                                      (49 (invokevirtual
					(methodCP "append" "java.lang.StringBuilder" ((class "java.lang.String")) (class "java.lang.StringBuilder"))))
                                      (52 (aload_0))
                                      (53 (iconst_3))
                                      (54 (baload))
                                      (55 (sipush 255))
                                      (58 (iand))
                                      (59 (invokevirtual
					(methodCP "append" "java.lang.StringBuilder" (int) (class "java.lang.StringBuilder"))))
                                      (62 (invokevirtual
					(methodCP "toString" "java.lang.StringBuilder" () (class "java.lang.String"))))
                                      (65 (areturn))
                                      (endofcode 66))
                                   (Exceptions )
                                   (StackMap )))
                        (method "init"
                              (parameters )
                              (returntype . void)
                              (accessflags  *class*  *native*  *private*  *static* )
                              (code))
                        (method "<clinit>"
                              (parameters )
                              (returntype . void)
                              (accessflags  *class*  *static* )
                              (code
                                   (max_stack . 0) (max_locals . 0) (code_length . 4)
                                   (parsedcode
                                      (0 (invokestatic
					(methodCP "init" "java.net.Inet4Address" () void)))
                                      (3 (return))
                                      (endofcode 4))
                                   (Exceptions )
                                   (StackMap ))))
            (interfaces)
            (accessflags  *class*  *final*  *public*  *super*  *synchronized* )
            (attributes
              (attribute "SourceFile")))))


(defconst *Inet4Address-class-table*
  (make-static-class-decls 
   *java.net.Inet4Address*))

(defconst *package-name-map* 
  ("java.net.Inet4Address" . "java.net"))

