; UUID-classtable.lisp
; Automatically generated by jvm2acl2 on Tue May 27 00:39:48 CDT 2014.
;

(defconst *java.util.UUID*
 (make-class-def
      '(class "java.util.UUID"
            "java.lang.Object"
            (constant_pool
                        (LONG -4856846361193249489)
                        (STRING  "data must be 16 bytes in length")
                        (STRING  "MD5")
                        (STRING  "MD5 not supported")
                        (STRING  "-")
                        (STRING  "Invalid UUID string: ")
                        (STRING  "0x")
                        (LONG 15)
                        (LONG 64)
                        (STRING  "Not a time-based UUID")
                        (LONG 4095)
                        (LONG 65535)
                        (LONG 4611404543450677248)
                        (LONG 281474976710655))
            (fields
                        (field "serialVersionUID" long (accessflags  *class*  *final*  *private*  *static* ) 0)
                        (field "mostSigBits" long (accessflags  *class*  *final*  *private* ) -1)
                        (field "leastSigBits" long (accessflags  *class*  *final*  *private* ) -1)
                        (field "numberGenerator" (class "java.security.SecureRandom") (accessflags  *class*  *private*  *static*  *volatile* ) -1)
                        (field "$assertionsDisabled" boolean (accessflags  *class*  *final*  *static* ) -1))
            (methods
                        (method "<init>"
                              (parameters (array byte))
                              (returntype . void)
                              (accessflags  *class*  *private* )
                              (code
                                   (max_stack . 4) (max_locals . 7) (code_length . 109)
                                   (parsedcode
                                      (0 (aload_0)) 
                                      (1 (invokespecial (methodCP "<init>" "java.lang.Object" () void))) 
                                      (4 (lconst_0)) 
                                      (5 (lstore_2)) 
                                      (6 (lconst_0)) 
                                      (7 (lstore 4)) 
                                      (9 (getstatic (fieldCP "$assertionsDisabled" "java.util.UUID" boolean))) 
                                      (12 (ifne 32)) ;;to TAG_0
                                      (15 (aload_1)) 
                                      (16 (arraylength)) 
                                      (17 (bipush 16)) 
                                      (19 (if_icmpeq 32)) ;;to TAG_0
                                      (22 (new (class "java.lang.AssertionError"))) 
                                      (25 (dup)) 
                                      (26 (ldc 1)) ;;STRING:: "data must be 16 bytes in length"
                                      (28 (invokespecial (methodCP "<init>" "java.lang.AssertionError" ((class "java.lang.Object")) void))) 
                                      (31 (athrow)) 
                                      (32 (iconst_0)) ;;at TAG_0
                                      (33 (istore 6)) 
                                      (35 (iload 6)) ;;at TAG_2
                                      (37 (bipush 8)) 
                                      (39 (if_icmpge 63)) ;;to TAG_1
                                      (42 (lload_2)) 
                                      (43 (bipush 8)) 
                                      (45 (lshl)) 
                                      (46 (aload_1)) 
                                      (47 (iload 6)) 
                                      (49 (baload)) 
                                      (50 (sipush 255)) 
                                      (53 (iand)) 
                                      (54 (i2l)) 
                                      (55 (lor)) 
                                      (56 (lstore_2)) 
                                      (57 (iinc 6 1)) 
                                      (60 (goto 35))  ;;to TAG_2
                                      (63 (bipush 8)) ;;at TAG_1
                                      (65 (istore 6)) 
                                      (67 (iload 6)) ;;at TAG_4
                                      (69 (bipush 16)) 
                                      (71 (if_icmpge 97)) ;;to TAG_3
                                      (74 (lload 4)) 
                                      (76 (bipush 8)) 
                                      (78 (lshl)) 
                                      (79 (aload_1)) 
                                      (80 (iload 6)) 
                                      (82 (baload)) 
                                      (83 (sipush 255)) 
                                      (86 (iand)) 
                                      (87 (i2l)) 
                                      (88 (lor)) 
                                      (89 (lstore 4)) 
                                      (91 (iinc 6 1)) 
                                      (94 (goto 67)) ;;to TAG_4
                                      (97 (aload_0)) ;;at TAG_3
                                      (98 (lload_2)) 
                                      (99 (putfield (fieldCP "mostSigBits" "java.util.UUID" long))) 
                                      (102 (aload_0)) 
                                      (103 (lload 4)) 
                                      (105 (putfield (fieldCP "leastSigBits" "java.util.UUID" long))) 
                                      (108 (return)) 
                                      (endofcode 109))
                                   (Exceptions )
                                   (StackMap )))
                        (method "<init>"
                              (parameters long long)
                              (returntype . void)
                              (accessflags  *class*  *public* )
                              (code
                                   (max_stack . 3) (max_locals . 5) (code_length . 15)
                                   (parsedcode
                                      (0 (aload_0))
                                      (1 (invokespecial
					(methodCP "<init>" "java.lang.Object" () void)))
                                      (4 (aload_0))
                                      (5 (lload_1))
                                      (6 (putfield (fieldCP "mostSigBits" "java.util.UUID" long)))
                                      (9 (aload_0))
                                      (10 (lload_3))
                                      (11 (putfield (fieldCP "leastSigBits" "java.util.UUID" long)))
                                      (14 (return))
                                      (endofcode 15))
                                   (Exceptions )
                                   (StackMap )))
                        (method "randomUUID"
                              (parameters )
                              (returntype . (class "java.util.UUID"))
                              (accessflags  *class*  *public*  *static* )
                              (code
                                   (max_stack . 4) (max_locals . 2) (code_length . 80)
                                   (parsedcode
                                      (0 (getstatic (fieldCP "numberGenerator" "java.util.UUID" (class "java.security.SecureRandom")))) 
                                      (3 (astore_0)) 
                                      (4 (aload_0)) 
                                      (5 (ifnonnull 20))  ;;to TAG_0
                                      (8 (new (class "java.security.SecureRandom"))) 
                                      (11 (dup)) 
                                      (12 (invokespecial (methodCP "<init>" "java.security.SecureRandom" () void))) 
                                      (15 (dup)) 
                                      (16 (astore_0)) 
                                      (17 (putstatic (fieldCP "numberGenerator" "java.util.UUID" (class "java.security.SecureRandom")))) 
                                      (20 (bipush 16)) ;;at TAG_0
                                      (22 (newarray BYTE)) 
                                      (24 (astore_1)) 
                                      (25 (aload_0)) 
                                      (26 (aload_1)) 
                                      (27 (invokevirtual (methodCP "nextBytes" "java.security.SecureRandom" ((array byte)) void))) 
                                      (30 (aload_1)) 
                                      (31 (bipush 6)) 
                                      (33 (dup2)) 
                                      (34 (baload)) 
                                      (35 (bipush 15)) 
                                      (37 (iand)) 
                                      (38 (i2b)) 
                                      (39 (bastore)) 
                                      (40 (aload_1)) 
                                      (41 (bipush 6)) 
                                      (43 (dup2)) 
                                      (44 (baload)) 
                                      (45 (bipush 64)) 
                                      (47 (ior)) 
                                      (48 (i2b)) 
                                      (49 (bastore)) 
                                      (50 (aload_1)) 
                                      (51 (bipush 8)) 
                                      (53 (dup2)) 
                                      (54 (baload)) 
                                      (55 (bipush 63)) 
                                      (57 (iand)) 
                                      (58 (i2b)) 
                                      (59 (bastore)) 
                                      (60 (aload_1)) 
                                      (61 (bipush 8)) 
                                      (63 (dup2)) 
                                      (64 (baload)) 
                                      (65 (sipush 128)) 
                                      (68 (ior)) 
                                      (69 (i2b)) 
                                      (70 (bastore)) 
                                      (71 (new (class "java.util.UUID"))) 
                                      (74 (dup)) 
                                      (75 (aload_1)) 
                                      (76 (invokespecial (methodCP "<init>" "java.util.UUID" ((array byte)) void))) 
                                      (79 (areturn)) 
                                      (endofcode 80))
                                   (Exceptions )
                                   (StackMap )))
                        (method "nameUUIDFromBytes"
                              (parameters (array byte))
                              (returntype . (class "java.util.UUID"))
                              (accessflags  *class*  *public*  *static* )
                              (code
                                   (max_stack . 4) (max_locals . 3) (code_length . 76)
                                   (parsedcode
                                      (0 (ldc 2)) ;;at TAG_1;;STRING:: "MD5"
                                      (2 (invokestatic (methodCP "getInstance" "java.security.MessageDigest" ((class "java.lang.String")) (class "java.security.MessageDigest")))) 
                                      (5 (astore_1)) 
                                      (6 (goto 20)) ;;to TAG_0;;at TAG_2
                                      (9 (astore_2)) ;;at TAG_3
                                      (10 (new (class "java.lang.InternalError"))) 
                                      (13 (dup)) 
                                      (14 (ldc 3)) ;;STRING:: "MD5 not supported"
                                      (16 (invokespecial (methodCP "<init>" "java.lang.InternalError" ((class "java.lang.String")) void))) 
                                      (19 (athrow)) 
                                      (20 (aload_1)) ;;at TAG_0
                                      (21 (aload_0)) 
                                      (22 (invokevirtual (methodCP "digest" "java.security.MessageDigest" ((array byte)) (array byte)))) 
                                      (25 (astore_2)) 
                                      (26 (aload_2)) 
                                      (27 (bipush 6)) 
                                      (29 (dup2)) 
                                      (30 (baload)) 
                                      (31 (bipush 15)) 
                                      (33 (iand)) 
                                      (34 (i2b)) 
                                      (35 (bastore)) 
                                      (36 (aload_2)) 
                                      (37 (bipush 6)) 
                                      (39 (dup2)) 
                                      (40 (baload)) 
                                      (41 (bipush 48)) 
                                      (43 (ior)) 
                                      (44 (i2b)) 
                                      (45 (bastore)) 
                                      (46 (aload_2)) 
                                      (47 (bipush 8)) 
                                      (49 (dup2)) 
                                      (50 (baload)) 
                                      (51 (bipush 63)) 
                                      (53 (iand)) 
                                      (54 (i2b)) 
                                      (55 (bastore)) 
                                      (56 (aload_2)) 
                                      (57 (bipush 8)) 
                                      (59 (dup2)) 
                                      (60 (baload)) 
                                      (61 (sipush 128)) 
                                      (64 (ior)) 
                                      (65 (i2b)) 
                                      (66 (bastore)) 
                                      (67 (new (class "java.util.UUID"))) 
                                      (70 (dup)) 
                                      (71 (aload_2)) 
                                      (72 (invokespecial (methodCP "<init>" "java.util.UUID" ((array byte)) void))) 
                                      (75 (areturn)) 
                                      (endofcode 76))
                                   (Exceptions 
                                     (handler 0 6  9 (class "java.security.NoSuchAlgorithmException")))
                                   (StackMap )))
                        (method "fromString"
                              (parameters (class "java.lang.String"))
                              (returntype . (class "java.util.UUID"))
                              (accessflags  *class*  *public*  *static* )
                              (code
                                   (max_stack . 6) (max_locals . 6) (code_length . 164)
                                   (parsedcode
                                      (0 (aload_0)) 
                                      (1 (ldc 4)) ;;STRING:: "-"
                                      (3 (invokevirtual (methodCP "split" "java.lang.String" ((class "java.lang.String")) (array (class "java.lang.String"))))) 
                                      (6 (astore_1)) 
                                      (7 (aload_1)) 
                                      (8 (arraylength)) 
                                      (9 (iconst_5)) 
                                      (10 (if_icmpeq 40)) ;;to TAG_0
                                      (13 (new (class "java.lang.IllegalArgumentException"))) 
                                      (16 (dup)) 
                                      (17 (new (class "java.lang.StringBuilder"))) 
                                      (20 (dup)) 
                                      (21 (invokespecial (methodCP "<init>" "java.lang.StringBuilder" () void))) 
                                      (24 (ldc 5)) ;;STRING:: "Invalid UUID string: "
                                      (26 (invokevirtual (methodCP "append" "java.lang.StringBuilder" ((class "java.lang.String")) (class "java.lang.StringBuilder")))) 
                                      (29 (aload_0)) 
                                      (30 (invokevirtual (methodCP "append" "java.lang.StringBuilder" ((class "java.lang.String")) (class "java.lang.StringBuilder")))) 
                                      (33 (invokevirtual (methodCP "toString" "java.lang.StringBuilder" () (class "java.lang.String")))) 
                                      (36 (invokespecial (methodCP "<init>" "java.lang.IllegalArgumentException" ((class "java.lang.String")) void))) 
                                      (39 (athrow)) 
                                      (40 (iconst_0)) ;;at TAG_0
                                      (41 (istore_2)) 
                                      (42 (iload_2)) ;;at TAG_2
                                      (43 (iconst_5)) 
                                      (44 (if_icmpge 77)) ;;to TAG_1
                                      (47 (aload_1)) 
                                      (48 (iload_2)) 
                                      (49 (new (class "java.lang.StringBuilder"))) 
                                      (52 (dup)) 
                                      (53 (invokespecial (methodCP "<init>" "java.lang.StringBuilder" () void))) 
                                      (56 (ldc 6)) ;;STRING:: "0x"
                                      (58 (invokevirtual (methodCP "append" "java.lang.StringBuilder" ((class "java.lang.String")) (class "java.lang.StringBuilder")))) 
                                      (61 (aload_1)) 
                                      (62 (iload_2)) 
                                      (63 (aaload)) 
                                      (64 (invokevirtual (methodCP "append" "java.lang.StringBuilder" ((class "java.lang.String")) (class "java.lang.StringBuilder")))) 
                                      (67 (invokevirtual (methodCP "toString" "java.lang.StringBuilder" () (class "java.lang.String")))) 
                                      (70 (aastore)) 
                                      (71 (iinc 2 1)) 
                                      (74 (goto 42))  ;;to TAG_2
                                      (77 (aload_1)) ;;at TAG_1
                                      (78 (iconst_0)) 
                                      (79 (aaload)) 
                                      (80 (invokestatic (methodCP "decode" "java.lang.Long" ((class "java.lang.String")) (class "java.lang.Long")))) 
                                      (83 (invokevirtual (methodCP "longValue" "java.lang.Long" () long))) 
                                      (86 (lstore_2)) 
                                      (87 (lload_2)) 
                                      (88 (bipush 16)) 
                                      (90 (lshl)) 
                                      (91 (lstore_2)) 
                                      (92 (lload_2)) 
                                      (93 (aload_1)) 
                                      (94 (iconst_1)) 
                                      (95 (aaload)) 
                                      (96 (invokestatic (methodCP "decode" "java.lang.Long" ((class "java.lang.String")) (class "java.lang.Long")))) 
                                      (99 (invokevirtual (methodCP "longValue" "java.lang.Long" () long))) 
                                      (102 (lor)) 
                                      (103 (lstore_2)) 
                                      (104 (lload_2)) 
                                      (105 (bipush 16)) 
                                      (107 (lshl)) 
                                      (108 (lstore_2)) 
                                      (109 (lload_2)) 
                                      (110 (aload_1)) 
                                      (111 (iconst_2)) 
                                      (112 (aaload)) 
                                      (113 (invokestatic (methodCP "decode" "java.lang.Long" ((class "java.lang.String")) (class "java.lang.Long")))) 
                                      (116 (invokevirtual (methodCP "longValue" "java.lang.Long" () long))) 
                                      (119 (lor)) 
                                      (120 (lstore_2)) 
                                      (121 (aload_1)) 
                                      (122 (iconst_3)) 
                                      (123 (aaload)) 
                                      (124 (invokestatic (methodCP "decode" "java.lang.Long" ((class "java.lang.String")) (class "java.lang.Long")))) 
                                      (127 (invokevirtual (methodCP "longValue" "java.lang.Long" () long))) 
                                      (130 (lstore 4)) 
                                      (132 (lload 4)) 
                                      (134 (bipush 48)) 
                                      (136 (lshl)) 
                                      (137 (lstore 4)) 
                                      (139 (lload 4)) 
                                      (141 (aload_1)) 
                                      (142 (iconst_4)) 
                                      (143 (aaload)) 
                                      (144 (invokestatic (methodCP "decode" "java.lang.Long" ((class "java.lang.String")) (class "java.lang.Long")))) 
                                      (147 (invokevirtual (methodCP "longValue" "java.lang.Long" () long))) 
                                      (150 (lor)) 
                                      (151 (lstore 4)) 
                                      (153 (new (class "java.util.UUID"))) 
                                      (156 (dup)) 
                                      (157 (lload_2)) 
                                      (158 (lload 4)) 
                                      (160 (invokespecial (methodCP "<init>" "java.util.UUID" (long long) void))) 
                                      (163 (areturn)) 
                                      (endofcode 164))
                                   (Exceptions )
                                   (StackMap )))
                        (method "getLeastSignificantBits"
                              (parameters )
                              (returntype . long)
                              (accessflags  *class*  *public* )
                              (code
                                   (max_stack . 2) (max_locals . 1) (code_length . 5)
                                   (parsedcode
                                      (0 (aload_0))
                                      (1 (getfield (fieldCP "leastSigBits" "java.util.UUID" long)))
                                      (4 (lreturn))
                                      (endofcode 5))
                                   (Exceptions )
                                   (StackMap )))
                        (method "getMostSignificantBits"
                              (parameters )
                              (returntype . long)
                              (accessflags  *class*  *public* )
                              (code
                                   (max_stack . 2) (max_locals . 1) (code_length . 5)
                                   (parsedcode
                                      (0 (aload_0))
                                      (1 (getfield (fieldCP "mostSigBits" "java.util.UUID" long)))
                                      (4 (lreturn))
                                      (endofcode 5))
                                   (Exceptions )
                                   (StackMap )))
                        (method "version"
                              (parameters )
                              (returntype . int)
                              (accessflags  *class*  *public* )
                              (code
                                   (max_stack . 4) (max_locals . 1) (code_length . 13)
                                   (parsedcode
                                      (0 (aload_0))
                                      (1 (getfield (fieldCP "mostSigBits" "java.util.UUID" long)))
                                      (4 (bipush 12))
                                      (6 (lshr))
                                      (7 (ldc2_w 7))      ;; LONG:: "15"
                                      (10 (land))
                                      (11 (l2i))
                                      (12 (ireturn))
                                      (endofcode 13))
                                   (Exceptions )
                                   (StackMap )))
                        (method "variant"
                              (parameters )
                              (returntype . int)
                              (accessflags  *class*  *public* )
                              (code
                                   (max_stack . 7) (max_locals . 1) (code_length . 27)
                                   (parsedcode
                                      (0 (aload_0))
                                      (1 (getfield (fieldCP "leastSigBits" "java.util.UUID" long)))
                                      (4 (ldc2_w 8))      ;; LONG:: "64"
                                      (7 (aload_0))
                                      (8 (getfield (fieldCP "leastSigBits" "java.util.UUID" long)))
                                      (11 (bipush 62))
                                      (13 (lushr))
                                      (14 (lsub))
                                      (15 (l2i))
                                      (16 (lushr))
                                      (17 (aload_0))
                                      (18 (getfield (fieldCP "leastSigBits" "java.util.UUID" long)))
                                      (21 (bipush 63))
                                      (23 (lshr))
                                      (24 (land))
                                      (25 (l2i))
                                      (26 (ireturn))
                                      (endofcode 27))
                                   (Exceptions )
                                   (StackMap )))
                        (method "timestamp"
                              (parameters )
                              (returntype . long)
                              (accessflags  *class*  *public* )
                              (code
                                   (max_stack . 6) (max_locals . 1) (code_length . 53)
                                   (parsedcode
                                      (0 (aload_0)) 
                                      (1 (invokevirtual (methodCP "version" "java.util.UUID" () int))) 
                                      (4 (iconst_1)) 
                                      (5 (if_icmpeq 18))  ;;to TAG_0
                                      (8 (new (class "java.lang.UnsupportedOperationException"))) 
                                      (11 (dup)) 
                                      (12 (ldc 9)) ;;STRING:: "Not a time-based UUID"
                                      (14 (invokespecial (methodCP "<init>" "java.lang.UnsupportedOperationException" ((class "java.lang.String")) void))) 
                                      (17 (athrow)) 
                                      (18 (aload_0)) ;;at TAG_0
                                      (19 (getfield (fieldCP "mostSigBits" "java.util.UUID" long))) 
                                      (22 (ldc2_w 10)) ;; LONG:: "4095"
                                      (25 (land)) 
                                      (26 (bipush 48)) 
                                      (28 (lshl)) 
                                      (29 (aload_0)) 
                                      (30 (getfield (fieldCP "mostSigBits" "java.util.UUID" long))) 
                                      (33 (bipush 16)) 
                                      (35 (lshr)) 
                                      (36 (ldc2_w 11)) ;; LONG:: "65535"
                                      (39 (land)) 
                                      (40 (bipush 32)) 
                                      (42 (lshl)) 
                                      (43 (lor)) 
                                      (44 (aload_0)) 
                                      (45 (getfield (fieldCP "mostSigBits" "java.util.UUID" long))) 
                                      (48 (bipush 32)) 
                                      (50 (lushr)) 
                                      (51 (lor)) 
                                      (52 (lreturn)) 
                                      (endofcode 53))
                                   (Exceptions )
                                   (StackMap )))
                        (method "clockSequence"
                              (parameters )
                              (returntype . int)
                              (accessflags  *class*  *public* )
                              (code
                                   (max_stack . 4) (max_locals . 1) (code_length . 31)
                                   (parsedcode
                                      (0 (aload_0)) 
                                      (1 (invokevirtual (methodCP "version" "java.util.UUID" () int))) 
                                      (4 (iconst_1)) 
                                      (5 (if_icmpeq 18))  ;;to TAG_0
                                      (8 (new (class "java.lang.UnsupportedOperationException"))) 
                                      (11 (dup)) 
                                      (12 (ldc 9)) ;;STRING:: "Not a time-based UUID"
                                      (14 (invokespecial (methodCP "<init>" "java.lang.UnsupportedOperationException" ((class "java.lang.String")) void))) 
                                      (17 (athrow)) 
                                      (18 (aload_0)) ;;at TAG_0
                                      (19 (getfield (fieldCP "leastSigBits" "java.util.UUID" long))) 
                                      (22 (ldc2_w 12)) ;; LONG:: "4611404543450677248"
                                      (25 (land)) 
                                      (26 (bipush 48)) 
                                      (28 (lushr)) 
                                      (29 (l2i)) 
                                      (30 (ireturn)) 
                                      (endofcode 31))
                                   (Exceptions )
                                   (StackMap )))
                        (method "node"
                              (parameters )
                              (returntype . long)
                              (accessflags  *class*  *public* )
                              (code
                                   (max_stack . 4) (max_locals . 1) (code_length . 27)
                                   (parsedcode
                                      (0 (aload_0)) 
                                      (1 (invokevirtual (methodCP "version" "java.util.UUID" () int))) 
                                      (4 (iconst_1)) 
                                      (5 (if_icmpeq 18))  ;;to TAG_0
                                      (8 (new (class "java.lang.UnsupportedOperationException"))) 
                                      (11 (dup)) 
                                      (12 (ldc 9)) ;;STRING:: "Not a time-based UUID"
                                      (14 (invokespecial (methodCP "<init>" "java.lang.UnsupportedOperationException" ((class "java.lang.String")) void))) 
                                      (17 (athrow)) 
                                      (18 (aload_0)) ;;at TAG_0
                                      (19 (getfield (fieldCP "leastSigBits" "java.util.UUID" long))) 
                                      (22 (ldc2_w 13)) ;; LONG:: "281474976710655"
                                      (25 (land)) 
                                      (26 (lreturn)) 
                                      (endofcode 27))
                                   (Exceptions )
                                   (StackMap )))
                        (method "toString"
                              (parameters )
                              (returntype . (class "java.lang.String"))
                              (accessflags  *class*  *public* )
                              (code
                                   (max_stack . 4) (max_locals . 1) (code_length . 97)
                                   (parsedcode
                                      (0 (new (class "java.lang.StringBuilder")))
                                      (3 (dup))
                                      (4 (invokespecial
					(methodCP "<init>" "java.lang.StringBuilder" () void)))
                                      (7 (aload_0))
                                      (8 (getfield (fieldCP "mostSigBits" "java.util.UUID" long)))
                                      (11 (bipush 32))
                                      (13 (lshr))
                                      (14 (bipush 8))
                                      (16 (invokestatic
					(methodCP "digits" "java.util.UUID" (long int) (class "java.lang.String"))))
                                      (19 (invokevirtual
					(methodCP "append" "java.lang.StringBuilder" ((class "java.lang.String")) (class "java.lang.StringBuilder"))))
                                      (22 (ldc 4))        ;;STRING:: "-"
                                      (24 (invokevirtual
					(methodCP "append" "java.lang.StringBuilder" ((class "java.lang.String")) (class "java.lang.StringBuilder"))))
                                      (27 (aload_0))
                                      (28 (getfield (fieldCP "mostSigBits" "java.util.UUID" long)))
                                      (31 (bipush 16))
                                      (33 (lshr))
                                      (34 (iconst_4))
                                      (35 (invokestatic
					(methodCP "digits" "java.util.UUID" (long int) (class "java.lang.String"))))
                                      (38 (invokevirtual
					(methodCP "append" "java.lang.StringBuilder" ((class "java.lang.String")) (class "java.lang.StringBuilder"))))
                                      (41 (ldc 4))        ;;STRING:: "-"
                                      (43 (invokevirtual
					(methodCP "append" "java.lang.StringBuilder" ((class "java.lang.String")) (class "java.lang.StringBuilder"))))
                                      (46 (aload_0))
                                      (47 (getfield (fieldCP "mostSigBits" "java.util.UUID" long)))
                                      (50 (iconst_4))
                                      (51 (invokestatic
					(methodCP "digits" "java.util.UUID" (long int) (class "java.lang.String"))))
                                      (54 (invokevirtual
					(methodCP "append" "java.lang.StringBuilder" ((class "java.lang.String")) (class "java.lang.StringBuilder"))))
                                      (57 (ldc 4))        ;;STRING:: "-"
                                      (59 (invokevirtual
					(methodCP "append" "java.lang.StringBuilder" ((class "java.lang.String")) (class "java.lang.StringBuilder"))))
                                      (62 (aload_0))
                                      (63 (getfield (fieldCP "leastSigBits" "java.util.UUID" long)))
                                      (66 (bipush 48))
                                      (68 (lshr))
                                      (69 (iconst_4))
                                      (70 (invokestatic
					(methodCP "digits" "java.util.UUID" (long int) (class "java.lang.String"))))
                                      (73 (invokevirtual
					(methodCP "append" "java.lang.StringBuilder" ((class "java.lang.String")) (class "java.lang.StringBuilder"))))
                                      (76 (ldc 4))        ;;STRING:: "-"
                                      (78 (invokevirtual
					(methodCP "append" "java.lang.StringBuilder" ((class "java.lang.String")) (class "java.lang.StringBuilder"))))
                                      (81 (aload_0))
                                      (82 (getfield (fieldCP "leastSigBits" "java.util.UUID" long)))
                                      (85 (bipush 12))
                                      (87 (invokestatic
					(methodCP "digits" "java.util.UUID" (long int) (class "java.lang.String"))))
                                      (90 (invokevirtual
					(methodCP "append" "java.lang.StringBuilder" ((class "java.lang.String")) (class "java.lang.StringBuilder"))))
                                      (93 (invokevirtual
					(methodCP "toString" "java.lang.StringBuilder" () (class "java.lang.String"))))
                                      (96 (areturn))
                                      (endofcode 97))
                                   (Exceptions )
                                   (StackMap )))
                        (method "digits"
                              (parameters long int)
                              (returntype . (class "java.lang.String"))
                              (accessflags  *class*  *private*  *static* )
                              (code
                                   (max_stack . 8) (max_locals . 5) (code_length . 21)
                                   (parsedcode
                                      (0 (lconst_1))
                                      (1 (iload_2))
                                      (2 (iconst_4))
                                      (3 (imul))
                                      (4 (lshl))
                                      (5 (lstore_3))
                                      (6 (lload_3))
                                      (7 (lload_0))
                                      (8 (lload_3))
                                      (9 (lconst_1))
                                      (10 (lsub))
                                      (11 (land))
                                      (12 (lor))
                                      (13 (invokestatic
					(methodCP "toHexString" "java.lang.Long" (long) (class "java.lang.String"))))
                                      (16 (iconst_1))
                                      (17 (invokevirtual
					(methodCP "substring" "java.lang.String" (int) (class "java.lang.String"))))
                                      (20 (areturn))
                                      (endofcode 21))
                                   (Exceptions )
                                   (StackMap )))
                        (method "hashCode"
                              (parameters )
                              (returntype . int)
                              (accessflags  *class*  *public* )
                              (code
                                   (max_stack . 4) (max_locals . 3) (code_length . 19)
                                   (parsedcode
                                      (0 (aload_0))
                                      (1 (getfield (fieldCP "mostSigBits" "java.util.UUID" long)))
                                      (4 (aload_0))
                                      (5 (getfield (fieldCP "leastSigBits" "java.util.UUID" long)))
                                      (8 (lxor))
                                      (9 (lstore_1))
                                      (10 (lload_1))
                                      (11 (bipush 32))
                                      (13 (lshr))
                                      (14 (l2i))
                                      (15 (lload_1))
                                      (16 (l2i))
                                      (17 (ixor))
                                      (18 (ireturn))
                                      (endofcode 19))
                                   (Exceptions )
                                   (StackMap )))
                        (method "equals"
                              (parameters (class "java.lang.Object"))
                              (returntype . boolean)
                              (accessflags  *class*  *public* )
                              (code
                                   (max_stack . 4) (max_locals . 3) (code_length . 52)
                                   (parsedcode
                                      (0 (aconst_null)) 
                                      (1 (aload_1)) 
                                      (2 (if_acmpeq 15)) ;;to TAG_0
                                      (5 (aload_1)) 
                                      (6 (invokevirtual (methodCP "getClass" "java.lang.Object" () (class "java.lang.Class")))) 
                                      (9 (ldc_w )) 
                                      (12 (if_acmpeq 17)) ;;to TAG_1
                                      (15 (iconst_0)) ;;at TAG_0
                                      (16 (ireturn)) 
                                      (17 (aload_1)) ;;at TAG_1
                                      (18 (checkcast (class "java.util.UUID"))) 
                                      (21 (astore_2)) 
                                      (22 (aload_0)) 
                                      (23 (getfield (fieldCP "mostSigBits" "java.util.UUID" long))) 
                                      (26 (aload_2)) 
                                      (27 (getfield (fieldCP "mostSigBits" "java.util.UUID" long))) 
                                      (30 (lcmp)) 
                                      (31 (ifne 50))  ;;to TAG_2
                                      (34 (aload_0)) 
                                      (35 (getfield (fieldCP "leastSigBits" "java.util.UUID" long))) 
                                      (38 (aload_2)) 
                                      (39 (getfield (fieldCP "leastSigBits" "java.util.UUID" long))) 
                                      (42 (lcmp)) 
                                      (43 (ifne 50))  ;;to TAG_2
                                      (46 (iconst_1)) 
                                      (47 (goto 51)) ;;to TAG_3
                                      (50 (iconst_0)) ;;at TAG_2
                                      (51 (ireturn)) ;;at TAG_3
                                      (endofcode 52))
                                   (Exceptions )
                                   (StackMap )))
                        (method "compareTo"
                              (parameters (class "java.util.UUID"))
                              (returntype . int)
                              (accessflags  *class*  *public* )
                              (code
                                   (max_stack . 4) (max_locals . 2) (code_length . 66)
                                   (parsedcode
                                      (0 (aload_0)) 
                                      (1 (getfield (fieldCP "mostSigBits" "java.util.UUID" long))) 
                                      (4 (aload_1)) 
                                      (5 (getfield (fieldCP "mostSigBits" "java.util.UUID" long))) 
                                      (8 (lcmp)) 
                                      (9 (ifge 16)) ;;to TAG_0
                                      (12 (iconst_m1)) 
                                      (13 (goto 65)) ;;to TAG_1
                                      (16 (aload_0)) ;;at TAG_0
                                      (17 (getfield (fieldCP "mostSigBits" "java.util.UUID" long))) 
                                      (20 (aload_1)) 
                                      (21 (getfield (fieldCP "mostSigBits" "java.util.UUID" long))) 
                                      (24 (lcmp)) 
                                      (25 (ifle 32))  ;;to TAG_2
                                      (28 (iconst_1)) 
                                      (29 (goto 65)) ;;to TAG_1
                                      (32 (aload_0)) ;;at TAG_2
                                      (33 (getfield (fieldCP "leastSigBits" "java.util.UUID" long))) 
                                      (36 (aload_1)) 
                                      (37 (getfield (fieldCP "leastSigBits" "java.util.UUID" long))) 
                                      (40 (lcmp)) 
                                      (41 (ifge 48)) ;;to TAG_3
                                      (44 (iconst_m1)) 
                                      (45 (goto 65)) ;;to TAG_1
                                      (48 (aload_0)) ;;at TAG_3
                                      (49 (getfield (fieldCP "leastSigBits" "java.util.UUID" long))) 
                                      (52 (aload_1)) 
                                      (53 (getfield (fieldCP "leastSigBits" "java.util.UUID" long))) 
                                      (56 (lcmp)) 
                                      (57 (ifle 64)) ;;to TAG_4
                                      (60 (iconst_1)) 
                                      (61 (goto 65)) ;;to TAG_1
                                      (64 (iconst_0)) ;;at TAG_4
                                      (65 (ireturn)) ;;at TAG_1
                                      (endofcode 66))
                                   (Exceptions )
                                   (StackMap )))
                        (method "compareTo"
                              (parameters (class "java.lang.Object"))
                              (returntype . int)
                              (accessflags  *class*  *public*  *volatile* )
                              (code
                                   (max_stack . 2) (max_locals . 2) (code_length . 9)
                                   (parsedcode
                                      (0 (aload_0))
                                      (1 (aload_1))
                                      (2 (checkcast (class "java.util.UUID")))
                                      (5 (invokevirtual
					(methodCP "compareTo" "java.util.UUID" ((class "java.util.UUID")) int)))
                                      (8 (ireturn))
                                      (endofcode 9))
                                   (Exceptions )
                                   (StackMap )))
                        (method "<clinit>"
                              (parameters )
                              (returntype . void)
                              (accessflags  *class*  *static* )
                              (code
                                   (max_stack . 1) (max_locals . 0) (code_length . 22)
                                   (parsedcode
                                      (0 (ldc_w )) 
                                      (3 (invokevirtual (methodCP "desiredAssertionStatus" "java.lang.Class" () boolean))) 
                                      (6 (ifne 13))  ;;to TAG_0
                                      (9 (iconst_1)) 
                                      (10 (goto 14)) ;;to TAG_1
                                      (13 (iconst_0)) ;;at TAG_0
                                      (14 (putstatic (fieldCP "$assertionsDisabled" "java.util.UUID" boolean))) ;;at TAG_1
                                      (17 (aconst_null)) 
                                      (18 (putstatic (fieldCP "numberGenerator" "java.util.UUID" (class "java.security.SecureRandom")))) 
                                      (21 (return)) 
                                      (endofcode 22))
                                   (Exceptions )
                                   (StackMap ))))
            (interfaces "java.io.Serializable" "java.lang.Comparable")
            (accessflags  *class*  *final*  *public*  *super*  *synchronized* )
            (attributes
              (attribute "SourceFile")
              (attribute "Signature")))))


(defconst *UUID-class-table*
  (make-static-class-decls 
   *java.util.UUID*))

(defconst *package-name-map* 
  ("java.util.UUID" . "java.util"))

