; Bits-classtable.lisp
; Automatically generated by jvm2acl2 on Tue May 27 00:39:31 CDT 2014.
;

(defconst *java.io.Bits*
 (make-class-def
      '(class "java.io.Bits"
            "java.lang.Object"
            (constant_pool
                        (LONG 255))
            (fields)
            (methods
                        (method "<init>"
                              (parameters )
                              (returntype . void)
                              (accessflags  *class* )
                              (code
                                   (max_stack . 1) (max_locals . 1) (code_length . 5)
                                   (parsedcode
                                      (0 (aload_0))
                                      (1 (invokespecial
					(methodCP "<init>" "java.lang.Object" () void)))
                                      (4 (return))
                                      (endofcode 5))
                                   (Exceptions )
                                   (StackMap )))
                        (method "getBoolean"
                              (parameters (array byte) int)
                              (returntype . boolean)
                              (accessflags  *class*  *static* )
                              (code
                                   (max_stack . 2) (max_locals . 2) (code_length . 12)
                                   (parsedcode
                                      (0 (aload_0)) 
                                      (1 (iload_1)) 
                                      (2 (baload)) 
                                      (3 (ifeq 10))  ;;to TAG_0
                                      (6 (iconst_1)) 
                                      (7 (goto 11)) ;;to TAG_1
                                      (10 (iconst_0)) ;;at TAG_0
                                      (11 (ireturn)) ;;at TAG_1
                                      (endofcode 12))
                                   (Exceptions )
                                   (StackMap )))
                        (method "getChar"
                              (parameters (array byte) int)
                              (returntype . char)
                              (accessflags  *class*  *static* )
                              (code
                                   (max_stack . 3) (max_locals . 2) (code_length . 18)
                                   (parsedcode
                                      (0 (aload_0))
                                      (1 (iload_1))
                                      (2 (iconst_1))
                                      (3 (iadd))
                                      (4 (baload))
                                      (5 (sipush 255))
                                      (8 (iand))
                                      (9 (aload_0))
                                      (10 (iload_1))
                                      (11 (baload))
                                      (12 (bipush 8))
                                      (14 (ishl))
                                      (15 (iadd))
                                      (16 (i2c))
                                      (17 (ireturn))
                                      (endofcode 18))
                                   (Exceptions )
                                   (StackMap )))
                        (method "getShort"
                              (parameters (array byte) int)
                              (returntype . short)
                              (accessflags  *class*  *static* )
                              (code
                                   (max_stack . 3) (max_locals . 2) (code_length . 18)
                                   (parsedcode
                                      (0 (aload_0))
                                      (1 (iload_1))
                                      (2 (iconst_1))
                                      (3 (iadd))
                                      (4 (baload))
                                      (5 (sipush 255))
                                      (8 (iand))
                                      (9 (aload_0))
                                      (10 (iload_1))
                                      (11 (baload))
                                      (12 (bipush 8))
                                      (14 (ishl))
                                      (15 (iadd))
                                      (16 (i2s))
                                      (17 (ireturn))
                                      (endofcode 18))
                                   (Exceptions )
                                   (StackMap )))
                        (method "getInt"
                              (parameters (array byte) int)
                              (returntype . int)
                              (accessflags  *class*  *static* )
                              (code
                                   (max_stack . 4) (max_locals . 2) (code_length . 43)
                                   (parsedcode
                                      (0 (aload_0))
                                      (1 (iload_1))
                                      (2 (iconst_3))
                                      (3 (iadd))
                                      (4 (baload))
                                      (5 (sipush 255))
                                      (8 (iand))
                                      (9 (aload_0))
                                      (10 (iload_1))
                                      (11 (iconst_2))
                                      (12 (iadd))
                                      (13 (baload))
                                      (14 (sipush 255))
                                      (17 (iand))
                                      (18 (bipush 8))
                                      (20 (ishl))
                                      (21 (iadd))
                                      (22 (aload_0))
                                      (23 (iload_1))
                                      (24 (iconst_1))
                                      (25 (iadd))
                                      (26 (baload))
                                      (27 (sipush 255))
                                      (30 (iand))
                                      (31 (bipush 16))
                                      (33 (ishl))
                                      (34 (iadd))
                                      (35 (aload_0))
                                      (36 (iload_1))
                                      (37 (baload))
                                      (38 (bipush 24))
                                      (40 (ishl))
                                      (41 (iadd))
                                      (42 (ireturn))
                                      (endofcode 43))
                                   (Exceptions )
                                   (StackMap )))
                        (method "getFloat"
                              (parameters (array byte) int)
                              (returntype . float)
                              (accessflags  *class*  *static* )
                              (code
                                   (max_stack . 2) (max_locals . 2) (code_length . 9)
                                   (parsedcode
                                      (0 (aload_0))
                                      (1 (iload_1))
                                      (2 (invokestatic
					(methodCP "getInt" "java.io.Bits" ((array byte) int) int)))
                                      (5 (invokestatic
					(methodCP "intBitsToFloat" "java.lang.Float" (int) float)))
                                      (8 (freturn))
                                      (endofcode 9))
                                   (Exceptions )
                                   (StackMap )))
                        (method "getLong"
                              (parameters (array byte) int)
                              (returntype . long)
                              (accessflags  *class*  *static* )
                              (code
                                   (max_stack . 6) (max_locals . 2) (code_length . 105)
                                   (parsedcode
                                      (0 (aload_0))
                                      (1 (iload_1))
                                      (2 (bipush 7))
                                      (4 (iadd))
                                      (5 (baload))
                                      (6 (i2l))
                                      (7 (ldc2_w 0))      ;; LONG:: "255"
                                      (10 (land))
                                      (11 (aload_0))
                                      (12 (iload_1))
                                      (13 (bipush 6))
                                      (15 (iadd))
                                      (16 (baload))
                                      (17 (i2l))
                                      (18 (ldc2_w 0))     ;; LONG:: "255"
                                      (21 (land))
                                      (22 (bipush 8))
                                      (24 (lshl))
                                      (25 (ladd))
                                      (26 (aload_0))
                                      (27 (iload_1))
                                      (28 (iconst_5))
                                      (29 (iadd))
                                      (30 (baload))
                                      (31 (i2l))
                                      (32 (ldc2_w 0))     ;; LONG:: "255"
                                      (35 (land))
                                      (36 (bipush 16))
                                      (38 (lshl))
                                      (39 (ladd))
                                      (40 (aload_0))
                                      (41 (iload_1))
                                      (42 (iconst_4))
                                      (43 (iadd))
                                      (44 (baload))
                                      (45 (i2l))
                                      (46 (ldc2_w 0))     ;; LONG:: "255"
                                      (49 (land))
                                      (50 (bipush 24))
                                      (52 (lshl))
                                      (53 (ladd))
                                      (54 (aload_0))
                                      (55 (iload_1))
                                      (56 (iconst_3))
                                      (57 (iadd))
                                      (58 (baload))
                                      (59 (i2l))
                                      (60 (ldc2_w 0))     ;; LONG:: "255"
                                      (63 (land))
                                      (64 (bipush 32))
                                      (66 (lshl))
                                      (67 (ladd))
                                      (68 (aload_0))
                                      (69 (iload_1))
                                      (70 (iconst_2))
                                      (71 (iadd))
                                      (72 (baload))
                                      (73 (i2l))
                                      (74 (ldc2_w 0))     ;; LONG:: "255"
                                      (77 (land))
                                      (78 (bipush 40))
                                      (80 (lshl))
                                      (81 (ladd))
                                      (82 (aload_0))
                                      (83 (iload_1))
                                      (84 (iconst_1))
                                      (85 (iadd))
                                      (86 (baload))
                                      (87 (i2l))
                                      (88 (ldc2_w 0))     ;; LONG:: "255"
                                      (91 (land))
                                      (92 (bipush 48))
                                      (94 (lshl))
                                      (95 (ladd))
                                      (96 (aload_0))
                                      (97 (iload_1))
                                      (98 (baload))
                                      (99 (i2l))
                                      (100 (bipush 56))
                                      (102 (lshl))
                                      (103 (ladd))
                                      (104 (lreturn))
                                      (endofcode 105))
                                   (Exceptions )
                                   (StackMap )))
                        (method "getDouble"
                              (parameters (array byte) int)
                              (returntype . double)
                              (accessflags  *class*  *static* )
                              (code
                                   (max_stack . 2) (max_locals . 2) (code_length . 9)
                                   (parsedcode
                                      (0 (aload_0))
                                      (1 (iload_1))
                                      (2 (invokestatic
					(methodCP "getLong" "java.io.Bits" ((array byte) int) long)))
                                      (5 (invokestatic
					(methodCP "longBitsToDouble" "java.lang.Double" (long) double)))
                                      (8 (dreturn))
                                      (endofcode 9))
                                   (Exceptions )
                                   (StackMap )))
                        (method "putBoolean"
                              (parameters (array byte) int boolean)
                              (returntype . void)
                              (accessflags  *class*  *static* )
                              (code
                                   (max_stack . 3) (max_locals . 3) (code_length . 14)
                                   (parsedcode
                                      (0 (aload_0)) 
                                      (1 (iload_1)) 
                                      (2 (iload_2)) 
                                      (3 (ifeq 10))  ;;to TAG_0
                                      (6 (iconst_1)) 
                                      (7 (goto 11)) ;;to TAG_1
                                      (10 (iconst_0)) ;;at TAG_0
                                      (11 (i2b)) ;;at TAG_1
                                      (12 (bastore)) 
                                      (13 (return)) 
                                      (endofcode 14))
                                   (Exceptions )
                                   (StackMap )))
                        (method "putChar"
                              (parameters (array byte) int char)
                              (returntype . void)
                              (accessflags  *class*  *static* )
                              (code
                                   (max_stack . 4) (max_locals . 3) (code_length . 16)
                                   (parsedcode
                                      (0 (aload_0))
                                      (1 (iload_1))
                                      (2 (iconst_1))
                                      (3 (iadd))
                                      (4 (iload_2))
                                      (5 (i2b))
                                      (6 (bastore))
                                      (7 (aload_0))
                                      (8 (iload_1))
                                      (9 (iload_2))
                                      (10 (bipush 8))
                                      (12 (iushr))
                                      (13 (i2b))
                                      (14 (bastore))
                                      (15 (return))
                                      (endofcode 16))
                                   (Exceptions )
                                   (StackMap )))
                        (method "putShort"
                              (parameters (array byte) int short)
                              (returntype . void)
                              (accessflags  *class*  *static* )
                              (code
                                   (max_stack . 4) (max_locals . 3) (code_length . 16)
                                   (parsedcode
                                      (0 (aload_0))
                                      (1 (iload_1))
                                      (2 (iconst_1))
                                      (3 (iadd))
                                      (4 (iload_2))
                                      (5 (i2b))
                                      (6 (bastore))
                                      (7 (aload_0))
                                      (8 (iload_1))
                                      (9 (iload_2))
                                      (10 (bipush 8))
                                      (12 (iushr))
                                      (13 (i2b))
                                      (14 (bastore))
                                      (15 (return))
                                      (endofcode 16))
                                   (Exceptions )
                                   (StackMap )))
                        (method "putInt"
                              (parameters (array byte) int int)
                              (returntype . void)
                              (accessflags  *class*  *static* )
                              (code
                                   (max_stack . 4) (max_locals . 3) (code_length . 36)
                                   (parsedcode
                                      (0 (aload_0))
                                      (1 (iload_1))
                                      (2 (iconst_3))
                                      (3 (iadd))
                                      (4 (iload_2))
                                      (5 (i2b))
                                      (6 (bastore))
                                      (7 (aload_0))
                                      (8 (iload_1))
                                      (9 (iconst_2))
                                      (10 (iadd))
                                      (11 (iload_2))
                                      (12 (bipush 8))
                                      (14 (iushr))
                                      (15 (i2b))
                                      (16 (bastore))
                                      (17 (aload_0))
                                      (18 (iload_1))
                                      (19 (iconst_1))
                                      (20 (iadd))
                                      (21 (iload_2))
                                      (22 (bipush 16))
                                      (24 (iushr))
                                      (25 (i2b))
                                      (26 (bastore))
                                      (27 (aload_0))
                                      (28 (iload_1))
                                      (29 (iload_2))
                                      (30 (bipush 24))
                                      (32 (iushr))
                                      (33 (i2b))
                                      (34 (bastore))
                                      (35 (return))
                                      (endofcode 36))
                                   (Exceptions )
                                   (StackMap )))
                        (method "putFloat"
                              (parameters (array byte) int float)
                              (returntype . void)
                              (accessflags  *class*  *static* )
                              (code
                                   (max_stack . 3) (max_locals . 3) (code_length . 10)
                                   (parsedcode
                                      (0 (aload_0))
                                      (1 (iload_1))
                                      (2 (fload_2))
                                      (3 (invokestatic
					(methodCP "floatToIntBits" "java.lang.Float" (float) int)))
                                      (6 (invokestatic
					(methodCP "putInt" "java.io.Bits" ((array byte) int int) void)))
                                      (9 (return))
                                      (endofcode 10))
                                   (Exceptions )
                                   (StackMap )))
                        (method "putLong"
                              (parameters (array byte) int long)
                              (returntype . void)
                              (accessflags  *class*  *static* )
                              (code
                                   (max_stack . 5) (max_locals . 4) (code_length . 86)
                                   (parsedcode
                                      (0 (aload_0))
                                      (1 (iload_1))
                                      (2 (bipush 7))
                                      (4 (iadd))
                                      (5 (lload_2))
                                      (6 (l2i))
                                      (7 (i2b))
                                      (8 (bastore))
                                      (9 (aload_0))
                                      (10 (iload_1))
                                      (11 (bipush 6))
                                      (13 (iadd))
                                      (14 (lload_2))
                                      (15 (bipush 8))
                                      (17 (lushr))
                                      (18 (l2i))
                                      (19 (i2b))
                                      (20 (bastore))
                                      (21 (aload_0))
                                      (22 (iload_1))
                                      (23 (iconst_5))
                                      (24 (iadd))
                                      (25 (lload_2))
                                      (26 (bipush 16))
                                      (28 (lushr))
                                      (29 (l2i))
                                      (30 (i2b))
                                      (31 (bastore))
                                      (32 (aload_0))
                                      (33 (iload_1))
                                      (34 (iconst_4))
                                      (35 (iadd))
                                      (36 (lload_2))
                                      (37 (bipush 24))
                                      (39 (lushr))
                                      (40 (l2i))
                                      (41 (i2b))
                                      (42 (bastore))
                                      (43 (aload_0))
                                      (44 (iload_1))
                                      (45 (iconst_3))
                                      (46 (iadd))
                                      (47 (lload_2))
                                      (48 (bipush 32))
                                      (50 (lushr))
                                      (51 (l2i))
                                      (52 (i2b))
                                      (53 (bastore))
                                      (54 (aload_0))
                                      (55 (iload_1))
                                      (56 (iconst_2))
                                      (57 (iadd))
                                      (58 (lload_2))
                                      (59 (bipush 40))
                                      (61 (lushr))
                                      (62 (l2i))
                                      (63 (i2b))
                                      (64 (bastore))
                                      (65 (aload_0))
                                      (66 (iload_1))
                                      (67 (iconst_1))
                                      (68 (iadd))
                                      (69 (lload_2))
                                      (70 (bipush 48))
                                      (72 (lushr))
                                      (73 (l2i))
                                      (74 (i2b))
                                      (75 (bastore))
                                      (76 (aload_0))
                                      (77 (iload_1))
                                      (78 (lload_2))
                                      (79 (bipush 56))
                                      (81 (lushr))
                                      (82 (l2i))
                                      (83 (i2b))
                                      (84 (bastore))
                                      (85 (return))
                                      (endofcode 86))
                                   (Exceptions )
                                   (StackMap )))
                        (method "putDouble"
                              (parameters (array byte) int double)
                              (returntype . void)
                              (accessflags  *class*  *static* )
                              (code
                                   (max_stack . 4) (max_locals . 4) (code_length . 10)
                                   (parsedcode
                                      (0 (aload_0))
                                      (1 (iload_1))
                                      (2 (dload_2))
                                      (3 (invokestatic
					(methodCP "doubleToLongBits" "java.lang.Double" (double) long)))
                                      (6 (invokestatic
					(methodCP "putLong" "java.io.Bits" ((array byte) int long) void)))
                                      (9 (return))
                                      (endofcode 10))
                                   (Exceptions )
                                   (StackMap ))))
            (interfaces)
            (accessflags  *class*  *super*  *synchronized* )
            (attributes
              (attribute "SourceFile")))))


(defconst *Bits-class-table*
  (make-static-class-decls 
   *java.io.Bits*))

(defconst *package-name-map* 
  ("java.io.Bits" . "java.io"))

